eclypse_core/graph/__init__.cpython-312-x86_64-linux-gnu.so
eclypse_core/graph/application.cpython-312-x86_64-linux-gnu.so
eclypse_core/graph/asset_graph.cpython-312-x86_64-linux-gnu.so
eclypse_core/graph/assets/__init__.cpython-312-x86_64-linux-gnu.so
eclypse_core/graph/assets/additive.cpython-312-x86_64-linux-gnu.so
eclypse_core/graph/assets/asset.cpython-312-x86_64-linux-gnu.so
eclypse_core/graph/assets/bucket.cpython-312-x86_64-linux-gnu.so
eclypse_core/graph/assets/concave.cpython-312-x86_64-linux-gnu.so
eclypse_core/graph/assets/convex.cpython-312-x86_64-linux-gnu.so
eclypse_core/graph/assets/multiplicative.cpython-312-x86_64-linux-gnu.so
eclypse_core/graph/assets/space.cpython-312-x86_64-linux-gnu.so
eclypse_core/graph/assets/symbolic.cpython-312-x86_64-linux-gnu.so
eclypse_core/graph/infrastructure.cpython-312-x86_64-linux-gnu.so
eclypse_core/graph/node_group.cpython-312-x86_64-linux-gnu.so
eclypse_core/placement/__init__.cpython-312-x86_64-linux-gnu.so
eclypse_core/placement/_manager.cpython-312-x86_64-linux-gnu.so
eclypse_core/placement/placement.cpython-312-x86_64-linux-gnu.so
eclypse_core/placement/strategy.cpython-312-x86_64-linux-gnu.so
eclypse_core/placement/view.cpython-312-x86_64-linux-gnu.so
eclypse_core/py.typed
eclypse_core/remote/__init__.cpython-312-x86_64-linux-gnu.so
eclypse_core/remote/_node/__init__.cpython-312-x86_64-linux-gnu.so
eclypse_core/remote/_node/node.cpython-312-x86_64-linux-gnu.so
eclypse_core/remote/_node/ops_thread.cpython-312-x86_64-linux-gnu.so
eclypse_core/remote/bootstrap/__init__.cpython-312-x86_64-linux-gnu.so
eclypse_core/remote/bootstrap/bootstrap.cpython-312-x86_64-linux-gnu.so
eclypse_core/remote/bootstrap/options_factory.cpython-312-x86_64-linux-gnu.so
eclypse_core/remote/communication/__init__.cpython-312-x86_64-linux-gnu.so
eclypse_core/remote/communication/interface.cpython-312-x86_64-linux-gnu.so
eclypse_core/remote/communication/mpi/__init__.cpython-312-x86_64-linux-gnu.so
eclypse_core-0.7.4.dist-info/LICENSE
eclypse_core-0.7.4.dist-info/METADATA
eclypse_core-0.7.4.dist-info/WHEEL
eclypse_core-0.7.4.dist-info/RECORD
