Metadata-Version: 2.1
Name: eclypse-core
Version: 0.7.4
Summary: Core package of the ECLYPSE framework.
License: MIT
Author: Jacopo Massa
Author-email: jacopo.massa@di.unipi.it
Maintainer: Jacopo Massa
Maintainer-email: jacopo.massa@di.unipi.it
Requires-Python: >=3.10,<3.14
Classifier: License :: OSI Approved :: MIT License
Classifier: Programming Language :: Python :: 3
Classifier: Programming Language :: Python :: 3.10
Classifier: Programming Language :: Python :: 3.11
Classifier: Programming Language :: Python :: 3.12
Classifier: Programming Language :: Python :: 3.13
Requires-Dist: loguru (>=0.7.3,<0.8.0)
Requires-Dist: networkx (>=3.2.1,<4.0.0)
